semantic/404.html
semantic/__init__.py
semantic/base.html
semantic/main.html
semantic/mkdocs_theme.yml
semantic/css/base.css
semantic/css/base.css.map
semantic/css/semantic.css
semantic/css/vs2015.min.css
semantic/css/themes/default/assets/fonts/brand-icons.eot
semantic/css/themes/default/assets/fonts/brand-icons.svg
semantic/css/themes/default/assets/fonts/brand-icons.ttf
semantic/css/themes/default/assets/fonts/brand-icons.woff
semantic/css/themes/default/assets/fonts/icons.eot
semantic/css/themes/default/assets/fonts/icons.svg
semantic/css/themes/default/assets/fonts/icons.ttf
semantic/css/themes/default/assets/fonts/icons.woff
semantic/css/themes/default/assets/fonts/outline-icons.eot
semantic/css/themes/default/assets/fonts/outline-icons.svg
semantic/css/themes/default/assets/fonts/outline-icons.ttf
semantic/css/themes/default/assets/fonts/outline-icons.woff
semantic/css/themes/default/assets/images/flags.png
semantic/includes/navbar.html
semantic/includes/search.html
semantic/includes/sidebar-sub-dropdown.html
semantic/includes/sidebar-subitem.html
semantic/includes/sidebar.html
semantic/js/base.js
semantic/js/highlight.min.js
semantic/js/jquery-3.3.1.js
semantic/js/semantic.js
mkdocs_semantic-1.0.0.dist-info/LICENSE
mkdocs_semantic-1.0.0.dist-info/METADATA
mkdocs_semantic-1.0.0.dist-info/WHEEL
mkdocs_semantic-1.0.0.dist-info/entry_points.txt
mkdocs_semantic-1.0.0.dist-info/top_level.txt
mkdocs_semantic-1.0.0.dist-info/RECORD
