Metadata-Version: 2.1
Name: mkdocs-semantic
Version: 1.0.0
Summary: Semantic-UI Theme for MkDocs
Home-page: http://mkdocs-semantic.alazy.dev/
Author: https://github.com/cryocaustik
Author-email: alex@alazy.dev
License: MIT
Platform: UNKNOWN
